manim_editor/__init__.py
manim_editor/__main__.py
manim_editor/app/__init__.py
manim_editor/app/error/__init__.py
manim_editor/app/error/handlers.py
manim_editor/app/error/templates/400.html
manim_editor/app/error/templates/401.html
manim_editor/app/error/templates/404.html
manim_editor/app/error/templates/418.html
manim_editor/app/error/templates/500.html
manim_editor/app/main/__init__.py
manim_editor/app/main/routes.py
manim_editor/app/main/templates/edit_project.html
manim_editor/app/main/templates/project_selection.html
manim_editor/app/main/templates/scene_selection.html
manim_editor/app/main/templates/set_project_name.html
manim_editor/app/static/img/arrow_clockwise.svg
manim_editor/app/static/img/banner.png
manim_editor/app/static/img/favicon.png
manim_editor/app/static/img/hourglass_split.svg
manim_editor/app/static/img/play_btn.svg
manim_editor/app/static/img/wind.svg
manim_editor/app/static/webpack/2b56e79ae5013246de29.woff2
manim_editor/app/static/webpack/38c4d2499557ae0379fd.woff
manim_editor/app/static/webpack/67475f65d9d8a1fe03a2.woff
manim_editor/app/static/webpack/base.css
manim_editor/app/static/webpack/base.js
manim_editor/app/static/webpack/base.js.LICENSE.txt
manim_editor/app/static/webpack/d0ec932c09e146590948.woff2
manim_editor/app/static/webpack/edit_project.js
manim_editor/app/static/webpack/scene_selection.js
manim_editor/app/templates/base.html
manim_editor/config.py
manim_editor/editor/__init__.py
manim_editor/editor/assets.py
manim_editor/editor/commands.py
manim_editor/editor/config.py
manim_editor/editor/create_project.py
manim_editor/editor/edit_project.py
manim_editor/editor/load_project.py
manim_editor/editor/manim_loader.py
manim_editor/editor/presentation_classes.py
manim_editor/project.schema.json
manim_editor/section_index.schema.json
manim_editor-0.3.8.dist-info/entry_points.txt
manim_editor-0.3.8.dist-info/LICENSE
manim_editor-0.3.8.dist-info/WHEEL
manim_editor-0.3.8.dist-info/METADATA
manim_editor-0.3.8.dist-info/RECORD
