Metadata-Version: 2.1
Name: manim-editor
Version: 0.3.8
Summary: Editor and Presenter for Manim Generated Content.
Home-page: https://github.com/ManimCommunity/manim_editor
License: MIT
Author: christopher-besch
Author-email: christopher.besch@gmx.de
Requires-Python: >=3.7,<4.0
Classifier: License :: OSI Approved :: MIT License
Classifier: Programming Language :: Python :: 3
Classifier: Programming Language :: Python :: 3.10
Classifier: Programming Language :: Python :: 3.7
Classifier: Programming Language :: Python :: 3.8
Classifier: Programming Language :: Python :: 3.9
Requires-Dist: Flask (>=2.0.2,<3.0.0)
Requires-Dist: click (>=8.0.3,<9.0.0)
Requires-Dist: jsonschema (>=4.1.2,<5.0.0)
Requires-Dist: manim (>=0.13.1,<0.14.0)
Requires-Dist: waitress (>=2.0.0,<3.0.0)
Project-URL: Documentation, https://docs.editor.manim.community
Project-URL: Repository, https://github.com/ManimCommunity/manim_editor
